langchain_ollama-1.0.0a1.dist-info/METADATA
langchain_ollama-1.0.0a1.dist-info/WHEEL
langchain_ollama-1.0.0a1.dist-info/entry_points.txt
langchain_ollama-1.0.0a1.dist-info/licenses/LICENSE
langchain_ollama/__init__.py
langchain_ollama/_compat.py
langchain_ollama/_utils.py
langchain_ollama/chat_models.py
langchain_ollama/embeddings.py
langchain_ollama/llms.py
langchain_ollama/py.typed
langchain_ollama-1.0.0a1.dist-info/RECORD
