Metadata-Version: 2.1
Name: langchain-ollama
Version: 1.0.0a1
Summary: An integration package connecting Ollama and LangChain
License: MIT
Project-URL: Source Code, https://github.com/langchain-ai/langchain/tree/master/libs/partners/ollama
Project-URL: Release Notes, https://github.com/langchain-ai/langchain/releases?q=tag%3A%22langchain-ollama%3D%3D0%22&expanded=true
Project-URL: repository, https://github.com/langchain-ai/langchain
Requires-Python: <4.0.0,>=3.10.0
Requires-Dist: ollama<1.0.0,>=0.6.0
Requires-Dist: langchain-core<2.0.0,>=1.0.0a6
